twtxt/__init__.py
twtxt/__main__.py
twtxt/cache.py
twtxt/cli.py
twtxt/config.py
twtxt/helper.py
twtxt/log.py
twtxt/mentions.py
twtxt/models.py
twtxt/parser.py
twtxt/twfile.py
twtxt/twhttp.py
twtxt-1.3.1.dist-info/AUTHORS
twtxt-1.3.1.dist-info/LICENSE
twtxt-1.3.1.dist-info/METADATA
twtxt-1.3.1.dist-info/WHEEL
twtxt-1.3.1.dist-info/entry_points.txt
twtxt-1.3.1.dist-info/top_level.txt
twtxt-1.3.1.dist-info/RECORD
