Metadata-Version: 2.1
Name: twtxt
Version: 1.3.1
Summary: Decentralised, minimalist microblogging service for hackers.
Home-page: https://github.com/buckket/twtxt
Author: buckket
Author-email: buckket@cock.li
License: MIT
Keywords: microblogging,twitter,twtxt
Platform: any
Classifier: Programming Language :: Python
Classifier: Programming Language :: Python :: 3
Classifier: Programming Language :: Python :: 3.7
Classifier: Programming Language :: Python :: 3.8
Classifier: Programming Language :: Python :: 3.9
Classifier: Programming Language :: Python :: 3.10
Classifier: Operating System :: OS Independent
Classifier: Development Status :: 5 - Production/Stable
Classifier: Environment :: Console
Classifier: License :: OSI Approved :: MIT License
Classifier: Intended Audience :: End Users/Desktop
Classifier: Topic :: Communications
Classifier: Topic :: Utilities
Requires-Python: >=3.7
License-File: LICENSE
License-File: AUTHORS
Requires-Dist: aiohttp (<4,>=3.8.1)
Requires-Dist: python-dateutil (<3,>=2.6.1)
Requires-Dist: humanize (<5,>=3.1.0)
Requires-Dist: click (<9,>=8.0.0)
Provides-Extra: dev
Requires-Dist: tox ; extra == 'dev'
Requires-Dist: pytest ; extra == 'dev'
Requires-Dist: pytest-cov ; extra == 'dev'
